nodal/__init__.py
nodal/demo.py
nodal/graph.py
nodal/graph_utils.py
nodal/core/__init__.py
nodal/core/callbacks.py
nodal/core/exceptions.py
nodal/core/nodes/__init__.py
nodal/core/nodes/base.py
nodal/nodes/__init__.py
nodal/nodes/noop.py
nodal/nodes/output.py
nodal/nodes/plus.py
nodal/nodes/text.py
tests/__init__.py
tests/nodal/__init__.py
tests/nodal/test_demo.py
tests/nodal/test_graph.py
tests/nodal/test_graph_utils.py
tests/nodal/core/__init__.py
tests/nodal/core/test_callbacks.py
tests/nodal/nodes/__init__.py
tests/nodal/nodes/test_nodes.py
tests/nodal/nodes/test_noop.py
tests/nodal/nodes/test_plus.py
tests/nodal/nodes/test_text.py
nodal-0.0.3.dist-info/LICENSE
nodal-0.0.3.dist-info/METADATA
nodal-0.0.3.dist-info/WHEEL
nodal-0.0.3.dist-info/top_level.txt
nodal-0.0.3.dist-info/RECORD
