Metadata-Version: 2.1
Name: nodal
Version: 0.0.3
Summary: An execution graph for Python tasks
Home-page: https://github.com/thimic/nodal
Author: Michael Thingnes
Author-email: thimic@gmail.com
License: UNKNOWN
Platform: UNKNOWN
Classifier: Programming Language :: Python :: 3
Classifier: License :: OSI Approved :: MIT License
Classifier: Operating System :: OS Independent
Requires-Python: >=3.7
